graphex_esxi_utils/__init__.py
graphex_esxi_utils/datatypes.py
graphex_esxi_utils/esxi_constants.py
graphex_esxi_utils/exceptions.py
graphex_esxi_utils/panos_constants.py
graphex_esxi_utils/actions/__init__.py
graphex_esxi_utils/actions/client.py
graphex_esxi_utils/actions/datastore.py
graphex_esxi_utils/actions/firewall.py
graphex_esxi_utils/actions/misc.py
graphex_esxi_utils/actions/network_misc.py
graphex_esxi_utils/actions/ovf.py
graphex_esxi_utils/actions/palo_alto_config.py
graphex_esxi_utils/actions/panos_api.py
graphex_esxi_utils/actions/portgroup.py
graphex_esxi_utils/actions/stack_monitoring.py
graphex_esxi_utils/actions/switch.py
graphex_esxi_utils/actions/temp_network.py
graphex_esxi_utils/actions/virtual_devices.py
graphex_esxi_utils/actions/vm.py
graphex_esxi_utils/actions/connection/__init__.py
graphex_esxi_utils/actions/connection/cisco.py
graphex_esxi_utils/actions/connection/interactive_ssh.py
graphex_esxi_utils/actions/connection/ssh.py
graphex_esxi_utils/actions/connection/unix.py
graphex_esxi_utils/actions/connection/winrm.py
graphex_esxi_utils/actions/vmtools/__init__.py
graphex_esxi_utils/actions/vmtools/generic_vm_tools.py
graphex_esxi_utils/actions/vmtools/panos_tools.py
graphex_esxi_utils/actions/vmtools/unix_tools.py
graphex_esxi_utils/actions/vmtools/windows_tools.py
graphex_esxi_utils/docs/convertMarkdown.bash
graphex_esxi_utils/docs/convertMarkdown.js
graphex_esxi_utils/docs/readme.txt
graphex_esxi_utils/docs/html/esxi.html
graphex_esxi_utils/docs/html/graphexStyle.css
graphex_esxi_utils/docs/html/index.html
graphex_esxi_utils/docs/html/keycodes.html
graphex_esxi_utils/docs/html/remote.html
graphex_esxi_utils/docs/markdown/esxi.md
graphex_esxi_utils/docs/markdown/graphexStyle.css
graphex_esxi_utils/docs/markdown/index.md
graphex_esxi_utils/docs/markdown/keycodes.md
graphex_esxi_utils/docs/markdown/remote.md
graphex_esxi_utils/docs/markdown/images/esxi_categories.png
graphex_esxi_utils/docs/markdown/images/esxi_connect.png
graphex_esxi_utils-1.9.3.dist-info/licenses/LICENSE
graphex_esxi_utils-1.9.3.dist-info/METADATA
graphex_esxi_utils-1.9.3.dist-info/WHEEL
graphex_esxi_utils-1.9.3.dist-info/top_level.txt
graphex_esxi_utils-1.9.3.dist-info/RECORD
