Metadata-Version: 2.4
Name: graphex-esxi-utils
Version: 1.9.3
Summary: A plugin for adding python esxi utils nodes to graphex.
Author: The MITRE Corporation
Requires-Python: >=3.10
License-File: LICENSE
Requires-Dist: mitre-graphex>=1.16.0
Requires-Dist: esxi-utils>=3.22
Requires-Dist: ping3==4.0.4
Requires-Dist: pexpect==4.8.0
Dynamic: author
Dynamic: license-file
Dynamic: requires-dist
Dynamic: requires-python
Dynamic: summary
